LICENSE
README.md
setup.py
algo_fun/__init__.py
algo_fun/get_dijkstra_shortest_path.py
algo_fun_dijkstra.egg-info/PKG-INFO
algo_fun_dijkstra.egg-info/SOURCES.txt
algo_fun_dijkstra.egg-info/dependency_links.txt
algo_fun_dijkstra.egg-info/top_level.txt
tests/__init__.py
tests/test_get_dijkstra_shortest_path.py