Metadata-Version: 2.1
Name: algo_fun_dijkstra
Version: 0.1.0
Summary: Find shortest path between vertices of a graph using the dijkstra algorithm
Home-page: https://gitlab.com/ChristopheLagaillarde/algo_fun_dijkstra
Author: Christophe Lagaillarde
Author-email: chrislag94@gmail.com
License: MIT
License-File: LICENSE
